markovsolver/__init__.py
markovsolver/markovsolver.py
markovsolver4safety-0.1.0.dist-info/METADATA
markovsolver4safety-0.1.0.dist-info/WHEEL
markovsolver4safety-0.1.0.dist-info/licenses/LICENSE
markovsolver4safety-0.1.0.dist-info/RECORD
