Metadata-Version: 2.3
Name: markovsolver4safety
Version: 0.1.0
Summary: Supports the Markov analysis used as safety substantiation presented in ARP4761A/ED-135.
Project-URL: Repository, https://github.com/samuelglorente/markovsolver4safety.git
Project-URL: Issues, https://github.com/samuelglorente/markovsolver4safety/issues
Author-email: Samuel Garcia Lorente <sglorente@proton.me>
License:                     GNU GENERAL PUBLIC LICENSE
License-File: LICENSE
Keywords: ARP4761A,ED135,Markov,RAMS,safety
Classifier: Development Status :: 3 - Alpha
Classifier: Programming Language :: Python
Requires-Python: >=3.10
Requires-Dist: lark==1.1.9
Requires-Dist: numpy==2.0.1
Requires-Dist: odeintw==1.0.2
Requires-Dist: pandas==2.2.2
Requires-Dist: python-dateutil==2.9.0.post0
Requires-Dist: pytz==2024.1
Requires-Dist: scipy==1.14.0
Requires-Dist: six==1.16.0
Requires-Dist: tzdata==2024.1
Provides-Extra: drawing-feature
Requires-Dist: pygraphviz==1.13; extra == 'drawing-feature'
Requires-Dist: unicodeitplus==0.3.1; extra == 'drawing-feature'
